mtg_card_api/__init__.py
mtg_card_api/_utils.py
mtg_card_api/mtg_scryfall_api.py
mtg_card_api-0.1.6.dist-info/METADATA
mtg_card_api-0.1.6.dist-info/WHEEL
mtg_card_api-0.1.6.dist-info/licenses/LICENSE
mtg_card_api-0.1.6.dist-info/RECORD
